{
  "subsection_title": "Peripheral Nerves",
  "parent_section": "X",
  "page_ref": "X12",
  "pages_processed": "752-754",
  "chunks_processed": 1,
  "table_structures_detected": {
    "multi_column": true,
    "has_h_p_columns": false,
    "has_asst_surg_anae": true,
    "has_time_requirements": false,
    "has_fee_amounts": true,
    "table_sections": []
  },
  "fee_codes": [
    {
      "code": "N188",
      "description": "minor nerve - including digital, cutaneous or lateral femoral cutaneous nerve",
      "fee": 153.7,
      "units": 7
    },
    {
      "code": "N285",
      "description": "major nerve - excluding carpal tunnel or ulnar nerve at elbow",
      "fee": 256.15,
      "units": 7
    },
    {
      "code": "N283",
      "description": "Decompression, exploration for thoracic outlet syndrome including excision of cervical and/or first rib and to include scalenotomy",
      "fee": 389.05,
      "units": 7
    },
    {
      "code": "N282",
      "description": "Brachial plexus (excluding thoracic outlet syndrome or cervical rib)",
      "fee": 1000.0,
      "units": 6
    },
    {
      "code": "N290",
      "description": "Carpal tunnel release",
      "fee": 156.75,
      "units": 6
    },
    {
      "code": "N190",
      "description": "Exploration and/or decompression and/or neurolysis of ulnar nerve (elbow)",
      "fee": 215.35,
      "units": 7
    },
    {
      "code": "N189",
      "description": "Ulnar nerve transposition at elbow - may include exploration, decompression and/or neurolysis",
      "fee": 279.25,
      "units": 7
    },
    {
      "code": "N177",
      "description": "Sciatic nerve in buttock",
      "fee": 430.75,
      "units": 7
    },
    {
      "code": "N184",
      "description": "Decompression of posterior tibial or common peroneal nerve",
      "fee": 165.2,
      "units": 7
    },
    {
      "code": "N286",
      "description": "Tumour or neuroma - major nerve",
      "fee": 317.85,
      "units": 7
    },
    {
      "code": "N295",
      "description": "Excision of Morton\u2019s or subcutaneous neuroma, glomus or small cutaneous nerve tumour",
      "fee": 109.95,
      "units": 6
    },
    {
      "code": "N289",
      "description": "minor - (sensory/cutaneous nerve)",
      "fee": 250.0,
      "units": 7
    },
    {
      "code": "N287",
      "description": "major - (mixed sensory and motor nerve, or pure motor nerve)",
      "fee": 500.0,
      "units": 7
    },
    {
      "code": "N293",
      "description": "minor \u2013 (sensory/cutaneous nerve)",
      "fee": 363.9,
      "units": 6
    },
    {
      "code": "N291",
      "description": "major \u2013 (mixed sensory and motor nerve, or pure motor nerve)",
      "fee": 727.8,
      "units": 6
    },
    {
      "code": "N183",
      "description": "minor - (sensory/cutaneous nerve)",
      "fee": 471.05,
      "units": 6
    },
    {
      "code": "N288",
      "description": "major - (mixed sensory and motor nerve, or pure motor nerve)",
      "fee": 927.55,
      "units": 6
    },
    {
      "code": "Z816",
      "description": "Implantation of electrode for peripheral nerve stimulation",
      "fee": 241.0,
      "units": 6
    },
    {
      "code": "Z823",
      "description": "Implantation or revision of stimulation pack or leads, (peripheral nerve, brain)",
      "fee": 404.3,
      "units": 8
    }
  ],
  "referenced_codes": [
    {
      "code": "E906",
      "context": "add 40% to basic fee for neurolysis, nerve tumour excision, nerve suture, nerve transfer, or nerve graft when using operating microscope",
      "description": "N/A",
      "source_subsection": "Peripheral Nerves",
      "source_page": "X12"
    },
    {
      "code": "E925",
      "context": "add 30% to basic fee for a repeat peripheral nerve procedure, or when acute nerve injury repair by suture, transfer or graft is delayed for more than 4 weeks",
      "description": "N/A",
      "source_subsection": "Peripheral Nerves",
      "source_page": "X12"
    },
    {
      "code": "E911",
      "context": "add 40% to N286 or N295 for implantation of neuroma into bone or muscle",
      "description": "N/A",
      "source_subsection": "Peripheral Nerves",
      "source_page": "X12"
    },
    {
      "code": "E899",
      "context": "add 102.45 for each additional cable, to N288",
      "description": "N/A",
      "source_subsection": "Peripheral Nerves",
      "source_page": "X12"
    }
  ],
  "rules": [],
  "notes": []
}